modbusim/__init__.py
modbusim/__main__.py
modbusim/simulator.py
modbusim-0.1.7.dist-info/LICENSE
modbusim-0.1.7.dist-info/METADATA
modbusim-0.1.7.dist-info/WHEEL
modbusim-0.1.7.dist-info/RECORD
