Metadata-Version: 2.3
Name: modbusim
Version: 0.1.7
Summary: A Modbus RTU/ASCII/TCP device simulator for testing and development
Author: Tom Sapletta
Author-email: info@softreck.dev
Requires-Python: >=3.8.1,<3.14
Classifier: Programming Language :: Python :: 3
Classifier: Programming Language :: Python :: 3.9
Classifier: Programming Language :: Python :: 3.10
Classifier: Programming Language :: Python :: 3.11
Classifier: Programming Language :: Python :: 3.12
Provides-Extra: dev
Requires-Dist: black (>=23.0.0) ; extra == "dev"
Requires-Dist: flake8 (>=6.0.0) ; extra == "dev"
Requires-Dist: isort (>=5.12.0) ; extra == "dev"
Requires-Dist: mypy (>=1.0.0) ; extra == "dev"
Requires-Dist: pytest (>=7.0.0) ; extra == "dev"
Requires-Dist: pytest-asyncio (>=0.20.0) ; extra == "dev"
Requires-Dist: pytest-cov (>=4.0.0) ; extra == "dev"
